flask_vite_transporter/__init__.py
flask_vite_transporter/cli.py
flask_vite_transporter/globals.py
flask_vite_transporter/vite_transporter.py
flask_vite_transporter/elements/__init__.py
flask_vite_transporter/elements/body_content.py
flask_vite_transporter/elements/link_tag.py
flask_vite_transporter/elements/script_tag.py
flask_vite_transporter/quart/__init__.py
flask_vite_transporter/utilities/__init__.py
flask_vite_transporter/utilities/compile_vite_apps.py
flask_vite_transporter/utilities/list_vite_apps.py
flask_vite_transporter/utilities/load_vite_app.py
flask_vite_transporter/utilities/print_help.py
flask_vite_transporter/utilities/pyproject_config.py
flask_vite_transporter/utilities/sprinkles.py
flask_vite_transporter-2.2.0.dist-info/entry_points.txt
flask_vite_transporter-2.2.0.dist-info/licenses/LICENSE
flask_vite_transporter-2.2.0.dist-info/WHEEL
flask_vite_transporter-2.2.0.dist-info/METADATA
flask_vite_transporter-2.2.0.dist-info/RECORD
