Metadata-Version: 2.4
Name: flask-vite-transporter
Version: 2.2.0
Summary: Transport Vite apps to Flask (or Quart).
Author-email: David Carmichael <david@uilix.com>
Requires-Python: >=3.9
Classifier: License :: OSI Approved :: MIT License
Classifier: Framework :: Flask
Classifier: Natural Language :: English
License-File: LICENSE
Requires-Dist: flask>=3.0.3
Requires-Dist: quart ; extra == "quart"
Provides-Extra: quart
